PythonHeJupyterJiqiXuexiRumenChuyiFix1/README.md
PythonHeJupyterJiqiXuexiRumenChuyiFix1/__init__.py
PythonHeJupyterJiqiXuexiRumenChuyiFix1/__main__.py
PythonHeJupyterJiqiXuexiRumenChuyiFix1/file.epub
PythonHeJupyterJiqiXuexiRumenChuyiFix1/index.html
PythonHeJupyterJiqiXuexiRumenChuyiFix1/css/__init__.py
PythonHeJupyterJiqiXuexiRumenChuyiFix1/css/annotations.css
PythonHeJupyterJiqiXuexiRumenChuyiFix1/css/main.css
PythonHeJupyterJiqiXuexiRumenChuyiFix1/css/normalize.css
PythonHeJupyterJiqiXuexiRumenChuyiFix1/css/popup.css
PythonHeJupyterJiqiXuexiRumenChuyiFix1/font/__init__.py
PythonHeJupyterJiqiXuexiRumenChuyiFix1/font/fontello.eot
PythonHeJupyterJiqiXuexiRumenChuyiFix1/font/fontello.svg
PythonHeJupyterJiqiXuexiRumenChuyiFix1/font/fontello.ttf
PythonHeJupyterJiqiXuexiRumenChuyiFix1/font/fontello.woff
PythonHeJupyterJiqiXuexiRumenChuyiFix1/img/__init__.py
PythonHeJupyterJiqiXuexiRumenChuyiFix1/img/annotator-glyph-sprite.png
PythonHeJupyterJiqiXuexiRumenChuyiFix1/img/annotator-icon-sprite.png
PythonHeJupyterJiqiXuexiRumenChuyiFix1/img/apple-touch-icon.png
PythonHeJupyterJiqiXuexiRumenChuyiFix1/img/cancelfullscreen.png
PythonHeJupyterJiqiXuexiRumenChuyiFix1/img/close.png
PythonHeJupyterJiqiXuexiRumenChuyiFix1/img/fullscreen.png
PythonHeJupyterJiqiXuexiRumenChuyiFix1/img/loader.gif
PythonHeJupyterJiqiXuexiRumenChuyiFix1/img/menu-icon.png
PythonHeJupyterJiqiXuexiRumenChuyiFix1/img/save.png
PythonHeJupyterJiqiXuexiRumenChuyiFix1/img/saved.png
PythonHeJupyterJiqiXuexiRumenChuyiFix1/img/settings-s.png
PythonHeJupyterJiqiXuexiRumenChuyiFix1/img/settings.png
PythonHeJupyterJiqiXuexiRumenChuyiFix1/img/star.png
PythonHeJupyterJiqiXuexiRumenChuyiFix1/js/__init__.py
PythonHeJupyterJiqiXuexiRumenChuyiFix1/js/epub.js
PythonHeJupyterJiqiXuexiRumenChuyiFix1/js/epub.min.js
PythonHeJupyterJiqiXuexiRumenChuyiFix1/js/epub.min.map
PythonHeJupyterJiqiXuexiRumenChuyiFix1/js/hooks.min.js
PythonHeJupyterJiqiXuexiRumenChuyiFix1/js/hooks.min.map
python_he_jupyter_jiqi_xuexi_rumen_chuyi_fix1-2025.3.25.1.dist-info/METADATA
python_he_jupyter_jiqi_xuexi_rumen_chuyi_fix1-2025.3.25.1.dist-info/WHEEL
python_he_jupyter_jiqi_xuexi_rumen_chuyi_fix1-2025.3.25.1.dist-info/entry_points.txt
python_he_jupyter_jiqi_xuexi_rumen_chuyi_fix1-2025.3.25.1.dist-info/top_level.txt
python_he_jupyter_jiqi_xuexi_rumen_chuyi_fix1-2025.3.25.1.dist-info/RECORD
